{
  "hook": "Bạn có biết chỉ 30 giây có thể dọn sạch mọi góc nhà?",
  "body": "Giới thiệu máy hút bụi mini siêu nhẹ, công suất mạnh, pin kéo dài 30 phút. Chỉ cần bật, lướt nhẹ qua sàn, thảm, ghế sofa, bụi bẩn tan biến ngay. Đặt trong túi, mang đi bất cứ đâu – từ phòng khách tới xe hơi, không còn rối rắm với dây cáp!",
  "cta": "Giá chỉ 250.000đ, mua ngay qua link affiliate trong bio, số lượng có hạn!",
  "full_script": "[Hook 0-3s] Bạn có biết chỉ 30 giây có thể dọn sạch mọi góc nhà? \n[Body 3-18s] Giới thiệu máy hút bụi mini siêu nhẹ, công suất mạnh, pin kéo dài 30 phút. Chỉ cần bật, lướt nhẹ qua sàn, thảm, ghế sofa, bụi bẩn tan biến ngay. Đặt trong túi, mang đi bất cứ đâu – từ phòng khách tới xe hơi, không còn rối rắm với dây cáp! \n[CTA 18-20s] Giá chỉ 250.000đ, mua ngay qua link affiliate trong bio, số lượng có hạn!",
  "hashtags": [
    "#máyhútbùi",
    "#mini",
    "#dọnnhanh",
    "#giárẻ",
    "#homecare"
  ],
  "estimated_duration_sec": 20
}